{"assets":{"BEBD35810A3D08E16C6B9833F06A83CE":{"type":"texture","index":1,"assetRequest":{"type":"slide","state":"contents","slide":"none"},"url":{"native":"assets\/9507E7B9-E817-4FDF-9AA0-066E686C901E.pdf"},"width":1024,"height":768},"3E08C9AE37B52F4C00FE1B0A02457B72":{"type":"texture","index":0,"assetRequest":{"type":"slide","state":"contents","slide":"none"},"url":{"native":"assets\/9507E7B9-E817-4FDF-9AA0-066E686C901E.pdf"},"width":1024,"height":768}},"events":[{"effects":[{"beginTime":0,"baseLayer":{"animations":[],"initialState":{"affineTransform":[1,0,0,1,0,0],"masksToBounds":false,"rotation":0,"scale":1,"position":{"pointX":512,"pointY":384},"width":1024,"sublayerTransform":[1,0,0,0,0,1,0,0,0,0,1,0,0,0,0,1],"contentsRect":{"y":0,"x":0,"width":1,"height":1},"opacity":1,"edgeAntialiasingMask":251658240,"height":768,"hidden":false,"anchorPoint":{"pointX":0.5,"pointY":0.5}},"objectID":"0","layers":[{"animations":[],"initialState":{"affineTransform":[1,0,0,1,0,0],"masksToBounds":false,"rotation":0,"scale":1,"position":{"pointX":512,"pointY":384},"width":1024,"sublayerTransform":[1,0,0,0,0,1,0,0,0,0,1,-0.00049229876906403734,0,0,0,1],"contentsRect":{"y":0,"x":0,"width":1,"height":1},"opacity":1,"edgeAntialiasingMask":251658240,"height":768,"hidden":false,"anchorPoint":{"pointX":0.5,"pointY":0.5}},"layers":[{"animations":[{"repeatCount":0,"timingControlPoint2y":0.9959721565246582,"from":{"pointX":1536,"pointY":384},"timingFunction":"custom","timeOffset":0,"autoreverses":false,"timingControlPoint1x":0.49705871939659119,"fillMode":"both","property":"position","duration":0.75,"beginTime":0,"timingControlPoint2x":0.49811732769012451,"timingControlPoint1y":0,"to":{"pointX":512,"pointY":384}}],"layers":[],"texturedRectangle":{"isBackgroundTexture":false,"singleTextureOpacity":1,"textureType":0,"textBaseline":0,"textXHeight":0,"isVerticalText":false},"initialState":{"affineTransform":[1,0,0,1,0,0],"masksToBounds":false,"rotation":0,"scale":1,"position":{"pointX":512,"pointY":384},"width":1024,"sublayerTransform":[1,0,0,0,0,1,0,0,0,0,1,0,0,0,0,1],"contentsRect":{"y":0,"x":0,"width":1,"height":1},"opacity":1,"edgeAntialiasingMask":0,"height":768,"hidden":false,"anchorPoint":{"pointX":0.5,"pointY":0.5}},"texture":"BEBD35810A3D08E16C6B9833F06A83CE"},{"animations":[{"repeatCount":0,"timingControlPoint2y":0.9959721565246582,"from":{"pointX":512,"pointY":384},"timingFunction":"custom","timeOffset":0,"autoreverses":false,"timingControlPoint1x":0.49705871939659119,"fillMode":"both","property":"position","duration":0.75,"beginTime":0,"timingControlPoint2x":0.49811732769012451,"timingControlPoint1y":0,"to":{"pointX":-512,"pointY":384}}],"layers":[],"texturedRectangle":{"isBackgroundTexture":false,"singleTextureOpacity":1,"textureType":0,"textBaseline":0,"textXHeight":0,"isVerticalText":false},"initialState":{"affineTransform":[1,0,0,1,0,0],"masksToBounds":false,"rotation":0,"scale":1,"position":{"pointX":512,"pointY":384},"width":1024,"sublayerTransform":[1,0,0,0,0,1,0,0,0,0,1,0,0,0,0,1],"contentsRect":{"y":0,"x":0,"width":1,"height":1},"opacity":1,"edgeAntialiasingMask":0,"height":768,"hidden":false,"anchorPoint":{"pointX":0.5,"pointY":0.5}},"texture":"3E08C9AE37B52F4C00FE1B0A02457B72"}]}]},"effects":[],"duration":0.75,"type":"transition","attributes":{"direction":12},"name":"apple:push","objectID":"0"}],"automaticPlay":false,"hyperlinks":[],"accessibility":[{"text":"S","targetRectangle":{"y":171.22517871856689,"x":934.58548557758331,"width":32.450000000000045,"height":59.549652099609375}},{"text":"T","targetRectangle":{"y":232.22517871856689,"x":935.53548557758336,"width":30.549999999999955,"height":59.549652099609375}},{"text":"R","targetRectangle":{"y":293.22517871856689,"x":932.76048557758327,"width":36.100000000000023,"height":59.549652099609375}},{"text":"I","targetRectangle":{"y":354.22517871856689,"x":943.43548557758334,"width":14.75,"height":59.549652099609375}},{"text":"N","targetRectangle":{"y":415.22517871856689,"x":932.28548557758336,"width":37.049999999999955,"height":59.549652099609375}},{"text":"G","targetRectangle":{"y":476.22517871856689,"x":931.83548557758331,"width":37.950000000000045,"height":59.549652099609375}},{"text":"S","targetRectangle":{"y":537.22517871856689,"x":934.58548557758331,"width":32.450000000000045,"height":59.549652099609375}},{"text":"iu.jpg","targetRectangle":{"y":-3.557373046875,"x":130.7960205078125,"width":762.407958984375,"height":775.11474609375}},{"text":"L\\u2028I","targetRectangle":{"y":140.72517204284668,"x":54.664524531364442,"width":36.649999999999999,"height":120.54965209960938}},{"text":"M","targetRectangle":{"y":262.72517204284668,"x":46.814524531364441,"width":45.349999999999994,"height":59.549652099609375}},{"text":"I\\u2028T\\u2028I\\u2028N\\u2028G","targetRectangle":{"y":323.72517204284668,"x":50.514524531364444,"width":44.5,"height":303.54965209960938}}],"baseLayer":{"animations":[],"initialState":{"affineTransform":[1,0,0,1,0,0],"masksToBounds":false,"rotation":0,"scale":1,"position":{"pointX":512,"pointY":384},"width":1024,"sublayerTransform":[1,0,0,0,0,1,0,0,0,0,1,0,0,0,0,1],"contentsRect":{"y":0,"x":0,"width":1,"height":1},"opacity":1,"edgeAntialiasingMask":251658240,"height":768,"hidden":false,"anchorPoint":{"pointX":0.5,"pointY":0.5}},"objectID":"0","layers":[{"animations":[],"initialState":{"affineTransform":[1,0,0,1,0,0],"masksToBounds":false,"rotation":0,"scale":1,"position":{"pointX":512,"pointY":384},"width":1024,"sublayerTransform":[1,0,0,0,0,1,0,0,0,0,1,-0.00049229876906403734,0,0,0,1],"contentsRect":{"y":0,"x":0,"width":1,"height":1},"opacity":1,"edgeAntialiasingMask":251658240,"height":768,"hidden":false,"anchorPoint":{"pointX":0.5,"pointY":0.5}},"layers":[{"animations":[],"layers":[],"texturedRectangle":{"isBackgroundTexture":false,"singleTextureOpacity":1,"textureType":0,"textBaseline":0,"textXHeight":0,"isVerticalText":false},"initialState":{"affineTransform":[1,0,0,1,0,0],"masksToBounds":false,"rotation":0,"scale":1,"position":{"pointX":512,"pointY":384},"width":1024,"sublayerTransform":[1,0,0,0,0,1,0,0,0,0,1,0,0,0,0,1],"contentsRect":{"y":0,"x":0,"width":1,"height":1},"opacity":1,"edgeAntialiasingMask":0,"height":768,"hidden":false,"anchorPoint":{"pointX":0.5,"pointY":0.5}},"texture":"3E08C9AE37B52F4C00FE1B0A02457B72"}]}]}}]}